tilemath/__init__.py
tilemath/py.typed
tilemath/mercantile/__init__.py
tilemath-0.1.1.dist-info/METADATA
tilemath-0.1.1.dist-info/WHEEL
tilemath-0.1.1.dist-info/licenses/LICENSE
tilemath-0.1.1.dist-info/RECORD
