Metadata-Version: 2.4
Name: tilemath
Version: 0.1.1
Summary: API-compatible replacement for the Mercantile library with full type safety.
Project-URL: Homepage, https://github.com/eddieland/tilemath
Project-URL: Repository, https://github.com/eddieland/tilemath
Project-URL: Bug Tracker, https://github.com/eddieland/tilemath/issues
Project-URL: Changelog, https://github.com/eddieland/tilemath/releases
Author-email: Edward Jones <e@eddie.land>
License: MIT License
License-File: LICENSE
Keywords: coordinates,geospatial,gis,mapping,mercantile,quadkey,slippy-map,spherical-mercator,tiles,web-mercator
Classifier: Development Status :: 4 - Beta
Classifier: Intended Audience :: Developers
Classifier: License :: OSI Approved :: MIT License
Classifier: Operating System :: OS Independent
Classifier: Programming Language :: Python
Classifier: Programming Language :: Python :: 3
Classifier: Programming Language :: Python :: 3.10
Classifier: Programming Language :: Python :: 3.11
Classifier: Programming Language :: Python :: 3.12
Classifier: Programming Language :: Python :: 3.13
Classifier: Topic :: Scientific/Engineering :: GIS
Classifier: Topic :: Software Development :: Libraries :: Python Modules
Classifier: Typing :: Typed
Requires-Python: <4.0,>=3.10
Requires-Dist: typing-extensions>=4.14.0
